appscanner/__init__.py
appscanner/exceptions.py
appscanner/services.py
appscanner/validators.py
appscanner/model/__init__.py
appscanner/model/assessment.py
appscanner/model/assessment_run_result.py
appscanner/model/assessment_runs.py
appscanner/model/helpers.py
appscanner/schemas/Assessment_run_results.xsd
appscanner/schemas/Assessments.xsd
appscanner/schemas/assessment_runs.xsd
python_trustwave_appscanner-0.2.11.dist-info/METADATA
python_trustwave_appscanner-0.2.11.dist-info/RECORD
python_trustwave_appscanner-0.2.11.dist-info/WHEEL
python_trustwave_appscanner-0.2.11.dist-info/top_level.txt
