Metadata-Version: 2.1
Name: python-trustwave-appscanner
Version: 0.2.11
Summary: A wrapper around the tapioca-trustwave-appscanner for translating the Appscanner API documents into Python Objects
Home-page: https://github.com/siteblindado/python-trustwave-appscanner
Author: Flávio Cardoso Ferreira Pontes
Author-email: flavio.pontes@siteblindado.com.br
License: MIT
Keywords: trustwave
Platform: UNKNOWN
Classifier: Development Status :: 5 - Production/Stable
Classifier: Intended Audience :: Developers
Classifier: License :: OSI Approved :: MIT License
Classifier: Natural Language :: English
Classifier: Programming Language :: Python :: 3.4
Classifier: Programming Language :: Python :: 3.5
Classifier: Programming Language :: Python :: 3.6
Requires-Python: >=3.3
Requires-Dist: tapioca-trustwave-appscanner (==0.7)
Requires-Dist: lxml (==4.2.1)
